[{
  "idUsuario": 1,
  "nombre": "Jacqueline Rice",
  "imagen": "http://dummyimage.com/418x336.png/cc0000/ffffff",
  "contrasena": "u3657v8AmWv7",
  "correoElectronico": "jrice0@google.com.hk",
  "tipoDocumento": "Evansville",
  "numeroDocumento": "3565210286684762",
  "dirreccion": "453 Fairfield Street",
  "telefono": "1-(812)868-6163",
  "reservas": [
    {
    },
    {
    },
    {
    }
  ],
  "viviendas": [
    {
    }
  ]
}, {
  "idUsuario": 2,
  "nombre": "Doris Carroll",
  "imagen": "http://dummyimage.com/403x425.bmp/ff4444/ffffff",
  "contrasena": "a9oiX4",
  "correoElectronico": "dcarroll1@thetimes.co.uk",
  "tipoDocumento": "Wenwucao",
  "numeroDocumento": "374288419097257",
  "dirreccion": "0451 Gerald Drive",
  "telefono": "86-(463)287-7003",
  "reservas": [
    {
    },
    {
    },
    {
    },
    {
    },
    {
    }
  ],
  "viviendas": [
    {
    }
  ]
}, {
  "idUsuario": 3,
  "nombre": "Fred Matthews",
  "imagen": "http://dummyimage.com/315x305.png/dddddd/000000",
  "contrasena": "ptqzqF52N2a5",
  "correoElectronico": "fmatthews2@w3.org",
  "tipoDocumento": "Duozhu",
  "numeroDocumento": "3532098964448240",
  "dirreccion": "2 Lindbergh Avenue",
  "telefono": "86-(844)530-7556",
  "reservas": [
    {
    },
    {
    },
    {
    },
    {
    }
  ],
  "viviendas": [
    {
    },
    {
    },
    {
    }
  ]
}, {
  "idUsuario": 4,
  "nombre": "Lois Day",
  "imagen": "http://dummyimage.com/380x424.jpg/ff4444/ffffff",
  "contrasena": "rr3FVgA",
  "correoElectronico": "lday3@globo.com",
  "tipoDocumento": "Juupajoki",
  "numeroDocumento": "5108756819533438",
  "dirreccion": "3 Algoma Street",
  "telefono": "358-(109)577-9598",
  "reservas": [
    {
    },
    {
    },
    {
    },
    {
    },
    {
    }
  ],
  "viviendas": [
    {
    },
    {
    }
  ]
}, {
  "idUsuario": 5,
  "nombre": "Jesse Kim",
  "imagen": "http://dummyimage.com/488x374.jpg/cc0000/ffffff",
  "contrasena": "U17AB2nvP",
  "correoElectronico": "jkim4@constantcontact.com",
  "tipoDocumento": "Cete",
  "numeroDocumento": "6333058435422035491",
  "dirreccion": "1339 Burrows Plaza",
  "telefono": "351-(788)739-4312",
  "reservas": [
    {
    },
    {
    },
    {
    },
    {
    },
    {
    }
  ],
  "viviendas": [
    {
    },
    {
    }
  ]
}, {
  "idUsuario": 6,
  "nombre": "Karen Alvarez",
  "imagen": "http://dummyimage.com/407x392.jpg/ff4444/ffffff",
  "contrasena": "cPjUBXWwxHy",
  "correoElectronico": "kalvarez5@bigcartel.com",
  "tipoDocumento": "Syriam",
  "numeroDocumento": "3564624377945984",
  "dirreccion": "9 Maywood Plaza",
  "telefono": "95-(558)641-9335",
  "reservas": [
    {
    },
    {
    },
    {
    },
    {
    }
  ],
  "viviendas": [
    {
    },
    {
    },
    {
    }
  ]
}, {
  "idUsuario": 7,
  "nombre": "Alan Meyer",
  "imagen": "http://dummyimage.com/313x409.bmp/ff4444/ffffff",
  "contrasena": "Uafahs",
  "correoElectronico": "ameyer6@squidoo.com",
  "tipoDocumento": "Majengo",
  "numeroDocumento": "201873841163972",
  "dirreccion": "7 Village Court",
  "telefono": "255-(938)876-9193",
  "reservas": [
    {
    },
    {
    },
    {
    },
    {
    }
  ],
  "viviendas": [
    {
    }
  ]
}, {
  "idUsuario": 8,
  "nombre": "Brian Lawson",
  "imagen": "http://dummyimage.com/460x307.bmp/dddddd/000000",
  "contrasena": "HaUZl64c",
  "correoElectronico": "blawson7@umich.edu",
  "tipoDocumento": "Evansville",
  "numeroDocumento": "4507267066819629",
  "dirreccion": "39119 Kinsman Road",
  "telefono": "1-(812)872-9891",
  "reservas": [
    {
    },
    {
    },
    {
    },
    {
    }
  ],
  "viviendas": [
    {
    }
  ]
}, {
  "idUsuario": 9,
  "nombre": "Nicole Barnes",
  "imagen": "http://dummyimage.com/401x322.bmp/ff4444/ffffff",
  "contrasena": "dGdqxL",
  "correoElectronico": "nbarnes8@xrea.com",
  "tipoDocumento": "Ichnya",
  "numeroDocumento": "3546556079951485",
  "dirreccion": "8637 Little Fleur Trail",
  "telefono": "380-(807)234-6481",
  "reservas": [
    {
    },
    {
    },
    {
    },
    {
    },
    {
    }
  ],
  "viviendas": [
    {
    },
    {
    }
  ]
}, {
  "idUsuario": 10,
  "nombre": "Bruce Miller",
  "imagen": "http://dummyimage.com/341x367.jpg/cc0000/ffffff",
  "contrasena": "dSVfilQ58RbE",
  "correoElectronico": "bmiller9@aboutads.info",
  "tipoDocumento": "Malaruhatan",
  "numeroDocumento": "3568171494937326",
  "dirreccion": "98958 Kedzie Place",
  "telefono": "63-(134)873-8828",
  "reservas": [
    {
    },
    {
    },
    {
    }
  ],
  "viviendas": [
    {
    }
  ]
}, {
  "idUsuario": 11,
  "nombre": "Robin Ramos",
  "imagen": "http://dummyimage.com/383x454.bmp/dddddd/000000",
  "contrasena": "CH254Bg",
  "correoElectronico": "rramosa@kickstarter.com",
  "tipoDocumento": "Rentian",
  "numeroDocumento": "3536701296640212",
  "dirreccion": "8 Sherman Lane",
  "telefono": "86-(439)300-1599",
  "reservas": [
    {
    },
    {
    },
    {
    }
  ],
  "viviendas": [
    {
    },
    {
    },
    {
    }
  ]
}, {
  "idUsuario": 12,
  "nombre": "Dorothy Patterson",
  "imagen": "http://dummyimage.com/405x325.png/ff4444/ffffff",
  "contrasena": "RtSaDHo",
  "correoElectronico": "dpattersonb@symantec.com",
  "tipoDocumento": "Sanxianling",
  "numeroDocumento": "5610740846854372",
  "dirreccion": "14 Marquette Trail",
  "telefono": "86-(934)805-1659",
  "reservas": [
    {
    },
    {
    },
    {
    },
    {
    }
  ],
  "viviendas": [
    {
    },
    {
    },
    {
    }
  ]
}, {
  "idUsuario": 13,
  "nombre": "Dorothy Gibson",
  "imagen": "http://dummyimage.com/333x500.png/5fa2dd/ffffff",
  "contrasena": "2zNeCs",
  "correoElectronico": "dgibsonc@go.com",
  "tipoDocumento": "Lushan",
  "numeroDocumento": "3540025367593983",
  "dirreccion": "2 Jenna Way",
  "telefono": "86-(266)463-3486",
  "reservas": [
    {
    },
    {
    },
    {
    }
  ],
  "viviendas": [
    {
    }
  ]
}, {
  "idUsuario": 14,
  "nombre": "Virginia Austin",
  "imagen": "http://dummyimage.com/480x460.png/5fa2dd/ffffff",
  "contrasena": "NzYXhFX2",
  "correoElectronico": "vaustind@ca.gov",
  "tipoDocumento": "Hancheng",
  "numeroDocumento": "4405091330504046",
  "dirreccion": "937 Thompson Avenue",
  "telefono": "86-(204)591-0735",
  "reservas": [
    {
    },
    {
    },
    {
    },
    {
    },
    {
    }
  ],
  "viviendas": [
    {
    },
    {
    },
    {
    }
  ]
}, {
  "idUsuario": 15,
  "nombre": "Ruth Evans",
  "imagen": "http://dummyimage.com/423x498.jpg/ff4444/ffffff",
  "contrasena": "s2oUmoTHWlK2",
  "correoElectronico": "revanse@dell.com",
  "tipoDocumento": "Sunampe",
  "numeroDocumento": "3540837311908335",
  "dirreccion": "0285 Logan Drive",
  "telefono": "51-(152)688-1750",
  "reservas": [
    {
    },
    {
    },
    {
    },
    {
    },
    {
    }
  ],
  "viviendas": [
    {
    },
    {
    },
    {
    }
  ]
}, {
  "idUsuario": 16,
  "nombre": "Bonnie Gray",
  "imagen": "http://dummyimage.com/493x315.png/cc0000/ffffff",
  "contrasena": "bKVWB3zDSIn",
  "correoElectronico": "bgrayf@cnbc.com",
  "tipoDocumento": "Kaniów",
  "numeroDocumento": "6334177079820775",
  "dirreccion": "4 Carey Alley",
  "telefono": "48-(308)856-4539",
  "reservas": [
    {
    },
    {
    },
    {
    },
    {
    }
  ],
  "viviendas": [
    {
    },
    {
    },
    {
    }
  ]
}, {
  "idUsuario": 17,
  "nombre": "Carl Berry",
  "imagen": "http://dummyimage.com/469x309.bmp/cc0000/ffffff",
  "contrasena": "vCcycjLPi",
  "correoElectronico": "cberryg@aboutads.info",
  "tipoDocumento": "Pandasan",
  "numeroDocumento": "3582575049222814",
  "dirreccion": "89875 Buell Alley",
  "telefono": "63-(484)714-9281",
  "reservas": [
    {
    },
    {
    },
    {
    },
    {
    }
  ],
  "viviendas": [
    {
    },
    {
    }
  ]
}, {
  "idUsuario": 18,
  "nombre": "Maria Franklin",
  "imagen": "http://dummyimage.com/305x446.bmp/5fa2dd/ffffff",
  "contrasena": "eAjQtU7SUAF",
  "correoElectronico": "mfranklinh@slashdot.org",
  "tipoDocumento": "Parista",
  "numeroDocumento": "3544980491465795",
  "dirreccion": "3090 Mitchell Road",
  "telefono": "63-(638)888-3386",
  "reservas": [
    {
    },
    {
    },
    {
    }
  ],
  "viviendas": [
    {
    }
  ]
}, {
  "idUsuario": 19,
  "nombre": "Jesse Cooper",
  "imagen": "http://dummyimage.com/348x301.bmp/ff4444/ffffff",
  "contrasena": "DmMKXz",
  "correoElectronico": "jcooperi@bbb.org",
  "tipoDocumento": "Los Guayos",
  "numeroDocumento": "4508251233531175",
  "dirreccion": "61 Lunder Lane",
  "telefono": "58-(705)374-0487",
  "reservas": [
    {
    },
    {
    },
    {
    }
  ],
  "viviendas": [
    {
    }
  ]
}, {
  "idUsuario": 20,
  "nombre": "Beverly Cox",
  "imagen": "http://dummyimage.com/456x458.png/5fa2dd/ffffff",
  "contrasena": "Kx3x5jgjEDyQ",
  "correoElectronico": "bcoxj@istockphoto.com",
  "tipoDocumento": "Mattaldi",
  "numeroDocumento": "633428236512055262",
  "dirreccion": "777 Debra Alley",
  "telefono": "54-(539)984-0135",
  "reservas": [
    {
    },
    {
    },
    {
    },
    {
    }
  ],
  "viviendas": [
    {
    },
    {
    }
  ]
}, {
  "idUsuario": 21,
  "nombre": "Joyce Ferguson",
  "imagen": "http://dummyimage.com/394x347.png/dddddd/000000",
  "contrasena": "741wAecU",
  "correoElectronico": "jfergusonk@instagram.com",
  "tipoDocumento": "Luz de Tavira",
  "numeroDocumento": "3572994260035767",
  "dirreccion": "128 Chinook Lane",
  "telefono": "351-(786)191-9614",
  "reservas": [
    {
    },
    {
    },
    {
    },
    {
    }
  ],
  "viviendas": [
    {
    }
  ]
}, {
  "idUsuario": 22,
  "nombre": "Mildred Jenkins",
  "imagen": "http://dummyimage.com/424x421.jpg/ff4444/ffffff",
  "contrasena": "R9uyoTOMf",
  "correoElectronico": "mjenkinsl@imdb.com",
  "tipoDocumento": "Kapakabisa",
  "numeroDocumento": "3557530094881858",
  "dirreccion": "32 Dapin Circle",
  "telefono": "62-(631)587-4886",
  "reservas": [
    {
    },
    {
    },
    {
    }
  ],
  "viviendas": [
    {
    }
  ]
}, {
  "idUsuario": 23,
  "nombre": "Joshua Cunningham",
  "imagen": "http://dummyimage.com/486x373.jpg/5fa2dd/ffffff",
  "contrasena": "6Kdztg",
  "correoElectronico": "jcunninghamm@mapy.cz",
  "tipoDocumento": "Bula",
  "numeroDocumento": "3578556387544213",
  "dirreccion": "253 Corry Point",
  "telefono": "63-(267)771-3254",
  "reservas": [
    {
    },
    {
    },
    {
    },
    {
    },
    {
    }
  ],
  "viviendas": [
    {
    },
    {
    }
  ]
}, {
  "idUsuario": 24,
  "nombre": "Albert Hernandez",
  "imagen": "http://dummyimage.com/353x300.jpg/ff4444/ffffff",
  "contrasena": "Lmhp8Lx0kv",
  "correoElectronico": "ahernandezn@webmd.com",
  "tipoDocumento": "Paitan",
  "numeroDocumento": "201865255315197",
  "dirreccion": "652 Bluestem Road",
  "telefono": "63-(437)965-9392",
  "reservas": [
    {
    },
    {
    },
    {
    },
    {
    }
  ],
  "viviendas": [
    {
    }
  ]
}, {
  "idUsuario": 25,
  "nombre": "Ann Ortiz",
  "imagen": "http://dummyimage.com/470x425.png/cc0000/ffffff",
  "contrasena": "xfoiMQWYdu",
  "correoElectronico": "aortizo@google.com",
  "tipoDocumento": "Kissónerga",
  "numeroDocumento": "4844152600721865",
  "dirreccion": "0529 Carey Avenue",
  "telefono": "357-(765)996-4112",
  "reservas": [
    {
    },
    {
    },
    {
    },
    {
    },
    {
    }
  ],
  "viviendas": [
    {
    }
  ]
}, {
  "idUsuario": 26,
  "nombre": "Kevin Johnston",
  "imagen": "http://dummyimage.com/316x443.jpg/5fa2dd/ffffff",
  "contrasena": "Qgq9Zk2dq3da",
  "correoElectronico": "kjohnstonp@state.tx.us",
  "tipoDocumento": "Żelistrzewo",
  "numeroDocumento": "3533619827428357",
  "dirreccion": "3658 Harper Way",
  "telefono": "48-(258)111-0783",
  "reservas": [
    {
    },
    {
    },
    {
    },
    {
    }
  ],
  "viviendas": [
    {
    }
  ]
}, {
  "idUsuario": 27,
  "nombre": "Patricia Hill",
  "imagen": "http://dummyimage.com/353x393.jpg/5fa2dd/ffffff",
  "contrasena": "QTt6siY2OCp",
  "correoElectronico": "phillq@pbs.org",
  "tipoDocumento": "Nowe Brzesko",
  "numeroDocumento": "3528344838435997",
  "dirreccion": "960 Laurel Crossing",
  "telefono": "48-(350)807-5226",
  "reservas": [
    {
    },
    {
    },
    {
    },
    {
    },
    {
    }
  ],
  "viviendas": [
    {
    },
    {
    }
  ]
}, {
  "idUsuario": 28,
  "nombre": "Heather Kennedy",
  "imagen": "http://dummyimage.com/363x387.png/dddddd/000000",
  "contrasena": "cgiPGKq8J",
  "correoElectronico": "hkennedyr@thetimes.co.uk",
  "tipoDocumento": "Palcamayo",
  "numeroDocumento": "3537911557199530",
  "dirreccion": "95 Welch Junction",
  "telefono": "51-(124)730-7251",
  "reservas": [
    {
    },
    {
    },
    {
    },
    {
    },
    {
    }
  ],
  "viviendas": [
    {
    },
    {
    },
    {
    }
  ]
}, {
  "idUsuario": 29,
  "nombre": "Bruce Brooks",
  "imagen": "http://dummyimage.com/472x429.png/5fa2dd/ffffff",
  "contrasena": "JMskzhZVyCX",
  "correoElectronico": "bbrookss@ning.com",
  "tipoDocumento": "Jiadingzhen",
  "numeroDocumento": "4405033980376739",
  "dirreccion": "3662 Oak Drive",
  "telefono": "86-(101)513-3489",
  "reservas": [
    {
    },
    {
    },
    {
    },
    {
    }
  ],
  "viviendas": [
    {
    },
    {
    }
  ]
}, {
  "idUsuario": 30,
  "nombre": "Harry Bowman",
  "imagen": "http://dummyimage.com/337x463.png/5fa2dd/ffffff",
  "contrasena": "9HGHV41",
  "correoElectronico": "hbowmant@google.ca",
  "tipoDocumento": "Abóboda",
  "numeroDocumento": "4903170133299936264",
  "dirreccion": "31 Acker Way",
  "telefono": "351-(221)283-0855",
  "reservas": [
    {
    },
    {
    },
    {
    },
    {
    }
  ],
  "viviendas": [
    {
    },
    {
    },
    {
    }
  ]
}]