[{
  "id": 1,
  "fechaDePago": "2017-03-11",
  "pago": "$2915.18",
  "tipoTramite": "ut suscipit a feugiat et eros vestibulum ac est lacinia nisi venenatis tristique fusce congue"
}, {
  "id": 2,
  "fechaDePago": "2016-07-16",
  "pago": "$846.36",
  "tipoTramite": "quis tortor id nulla ultrices aliquet maecenas leo odio condimentum"
}, {
  "id": 3,
  "fechaDePago": "2016-07-03",
  "pago": "$5037.98",
  "tipoTramite": "risus auctor sed tristique in tempus sit amet sem fusce consequat nulla nisl nunc nisl"
}, {
  "id": 4,
  "fechaDePago": "2017-03-10",
  "pago": "$3514.86",
  "tipoTramite": "erat quisque erat eros viverra eget congue eget semper rutrum nulla"
}, {
  "id": 5,
  "fechaDePago": "2017-03-13",
  "pago": "$2550.16",
  "tipoTramite": "aliquam convallis nunc proin at turpis a pede posuere nonummy integer non velit donec diam neque vestibulum eget vulputate"
}, {
  "id": 6,
  "fechaDePago": "2017-01-23",
  "pago": "$4602.68",
  "tipoTramite": "ultrices phasellus id sapien in sapien iaculis congue vivamus metus arcu"
}, {
  "id": 7,
  "fechaDePago": "2016-05-05",
  "pago": "$6749.99",
  "tipoTramite": "laoreet ut rhoncus aliquet pulvinar sed nisl nunc rhoncus dui vel sem sed sagittis nam congue risus semper"
}, {
  "id": 8,
  "fechaDePago": "2016-09-05",
  "pago": "$1616.99",
  "tipoTramite": "nullam porttitor lacus at turpis donec posuere metus vitae ipsum aliquam non mauris morbi non lectus aliquam"
}, {
  "id": 9,
  "fechaDePago": "2016-07-04",
  "pago": "$3844.99",
  "tipoTramite": "sapien a libero nam dui proin leo odio porttitor id consequat in consequat ut nulla sed accumsan"
}, {
  "id": 10,
  "fechaDePago": "2017-01-12",
  "pago": "$5960.86",
  "tipoTramite": "pulvinar lobortis est phasellus sit amet erat nulla tempus vivamus in felis eu sapien cursus vestibulum proin eu"
}, {
  "id": 11,
  "fechaDePago": "2016-12-10",
  "pago": "$3688.20",
  "tipoTramite": "nunc donec quis orci eget orci vehicula condimentum curabitur in libero ut massa volutpat convallis morbi odio"
}, {
  "id": 12,
  "fechaDePago": "2017-03-02",
  "pago": "$1324.83",
  "tipoTramite": "vitae consectetuer eget rutrum at lorem integer tincidunt ante vel ipsum praesent blandit lacinia erat vestibulum sed"
}, {
  "id": 13,
  "fechaDePago": "2016-08-24",
  "pago": "$4354.87",
  "tipoTramite": "non pretium quis lectus suspendisse potenti in eleifend quam a odio in hac habitasse platea dictumst maecenas ut massa"
}, {
  "id": 14,
  "fechaDePago": "2016-08-04",
  "pago": "$2876.22",
  "tipoTramite": "arcu adipiscing molestie hendrerit at vulputate vitae nisl aenean lectus pellentesque eget nunc donec quis orci"
}, {
  "id": 15,
  "fechaDePago": "2017-02-13",
  "pago": "$6321.08",
  "tipoTramite": "felis donec semper sapien a libero nam dui proin leo odio"
}, {
  "id": 16,
  "fechaDePago": "2017-01-16",
  "pago": "$1901.01",
  "tipoTramite": "duis faucibus accumsan odio curabitur convallis duis consequat dui nec nisi volutpat eleifend"
}, {
  "id": 17,
  "fechaDePago": "2016-09-27",
  "pago": "$4696.60",
  "tipoTramite": "primis in faucibus orci luctus et ultrices posuere cubilia curae mauris"
}, {
  "id": 18,
  "fechaDePago": "2017-03-27",
  "pago": "$4239.42",
  "tipoTramite": "rutrum nulla tellus in sagittis dui vel nisl duis ac nibh fusce lacus purus aliquet at feugiat non"
}, {
  "id": 19,
  "fechaDePago": "2017-02-27",
  "pago": "$6088.52",
  "tipoTramite": "sem mauris laoreet ut rhoncus aliquet pulvinar sed nisl nunc rhoncus dui vel sem sed sagittis nam congue"
}, {
  "id": 20,
  "fechaDePago": "2016-10-28",
  "pago": "$5680.18",
  "tipoTramite": "odio justo sollicitudin ut suscipit a feugiat et eros vestibulum ac est lacinia nisi venenatis tristique"
}, {
  "id": 21,
  "fechaDePago": "2016-12-29",
  "pago": "$5499.25",
  "tipoTramite": "posuere cubilia curae nulla dapibus dolor vel est donec odio justo sollicitudin ut suscipit"
}, {
  "id": 22,
  "fechaDePago": "2016-06-25",
  "pago": "$7631.41",
  "tipoTramite": "nulla ut erat id mauris vulputate elementum nullam varius nulla facilisi"
}, {
  "id": 23,
  "fechaDePago": "2016-12-17",
  "pago": "$3359.07",
  "tipoTramite": "hac habitasse platea dictumst maecenas ut massa quis augue luctus tincidunt nulla mollis"
}, {
  "id": 24,
  "fechaDePago": "2017-01-23",
  "pago": "$7396.76",
  "tipoTramite": "nulla justo aliquam quis turpis eget elit sodales scelerisque mauris sit amet eros suspendisse accumsan tortor quis turpis sed ante"
}, {
  "id": 25,
  "fechaDePago": "2017-03-15",
  "pago": "$4707.68",
  "tipoTramite": "duis aliquam convallis nunc proin at turpis a pede posuere nonummy"
}, {
  "id": 26,
  "fechaDePago": "2017-01-23",
  "pago": "$6334.39",
  "tipoTramite": "integer ac neque duis bibendum morbi non quam nec dui luctus rutrum nulla tellus"
}, {
  "id": 27,
  "fechaDePago": "2016-06-28",
  "pago": "$6578.20",
  "tipoTramite": "vestibulum quam sapien varius ut blandit non interdum in ante vestibulum ante ipsum primis"
}, {
  "id": 28,
  "fechaDePago": "2016-12-18",
  "pago": "$268.82",
  "tipoTramite": "non mi integer ac neque duis bibendum morbi non quam nec dui"
}, {
  "id": 29,
  "fechaDePago": "2017-03-30",
  "pago": "$2530.50",
  "tipoTramite": "condimentum id luctus nec molestie sed justo pellentesque viverra pede ac"
}, {
  "id": 30,
  "fechaDePago": "2016-04-23",
  "pago": "$7610.68",
  "tipoTramite": "in tempus sit amet sem fusce consequat nulla nisl nunc nisl duis bibendum felis sed interdum venenatis turpis enim"
}]